barcodex/__init__.py
barcodex-1.0.9.dist-info/LICENSE
barcodex-1.0.9.dist-info/METADATA
barcodex-1.0.9.dist-info/WHEEL
barcodex-1.0.9.dist-info/entry_points.txt
barcodex-1.0.9.dist-info/top_level.txt
barcodex-1.0.9.dist-info/RECORD
