Metadata-Version: 2.1
Name: barcodex
Version: 1.0.9
Summary: A tool for extracting Unique Molecular Identifiers (UMIs)                 from single or paired-end read sequences
Home-page: https://github.com/oicr-gsi/barcodex
Author: Richard Jovelin
Author-email: richard.jovelin@oicr.on.ca
License: MIT License
Keywords: computational genomics
Platform: UNKNOWN
Classifier: Development Status :: 3 - Alpha
Classifier: Intended Audience :: Science/Research
Classifier: Intended Audience :: Developers
Classifier: License :: OSI Approved :: MIT License
Classifier: Programming Language :: Python :: 3
Classifier: Programming Language :: Python :: 3.6
Classifier: Topic :: Software Development
Classifier: Topic :: Scientific/Engineering
Classifier: Operating System :: POSIX
Classifier: Operating System :: Unix
Classifier: Operating System :: MacOS
Classifier: Operating System :: Microsoft :: Windows
Requires-Python: >=3.6
Requires-Dist: regex (>=2020.6.8)
